pymcdm_reidentify/__init__.py
pymcdm_reidentify/normalizations.py
pymcdm_reidentify/methods/__init__.py
pymcdm_reidentify/methods/sesp.py
pymcdm_reidentify/methods/sfn.py
pymcdm_reidentify/methods/sitcom.py
pymcdm_reidentify/methods/sitw.py
pymcdm_reidentify/methods/sitwlocal.py
pymcdm_reidentify/methods/stfn.py
pymcdm_reidentify/methods/stochastic_identification.py
pymcdm_reidentify/methods/strfn.py
pymcdm_reidentify/methods/comet_tools/__init__.py
pymcdm_reidentify/methods/comet_tools/ml_expert.py
pymcdm_reidentify/visuals/__init__.py
pymcdm_reidentify/visuals/fitness_plot.py
pymcdm_reidentify/visuals/model_contourf.py
pymcdm_reidentify/visuals/tfn_plot.py
pymcdm_reidentify/visuals/trfn_plot.py
pymcdm_reidentify/visuals/weights_diff_plot.py
pymcdm_reidentify-1.0.2.dist-info/LICENSE
pymcdm_reidentify-1.0.2.dist-info/METADATA
pymcdm_reidentify-1.0.2.dist-info/WHEEL
pymcdm_reidentify-1.0.2.dist-info/top_level.txt
pymcdm_reidentify-1.0.2.dist-info/RECORD
