Metadata-Version: 2.1
Name: pymcdm_reidentify
Version: 1.0.2
Summary: Python library for reidnetification of multi-criteria models
Author-email: Bartłomiej Kizielewicz <bartlomiej-kizielewicz@zut.edu.pl>
Classifier: Programming Language :: Python :: 3
Classifier: License :: OSI Approved :: MIT License
Classifier: Operating System :: OS Independent
Requires-Python: >=3.11
License-File: LICENSE
Requires-Dist: numpy
Requires-Dist: pymcdm
Requires-Dist: mealpy ==3.0.1
Requires-Dist: matplotlib
Provides-Extra: docs
Requires-Dist: sphinx-autoapi ; extra == 'docs'
Requires-Dist: nbsphinx ; extra == 'docs'
Requires-Dist: IPython ; extra == 'docs'
Requires-Dist: myst-parser ; extra == 'docs'
Requires-Dist: sphinx-rtd-theme ; extra == 'docs'
Requires-Dist: recommonmark ; extra == 'docs'
Requires-Dist: pandoc ; extra == 'docs'
